flowlogger/__init__.py
flowlogger/logger/__init__.py
flowlogger/logger/length_time/__init__.py
flowlogger/logger/length_time/length_time.py
flowlogger/logger/length_time/length_time_class.py
flowlogger/logger/system_status/__init__.py
flowlogger/logger/system_status/hardware_usage.py
flowlogger/logger/system_status/ram_status.py
flowlogger/utils/__init__.py
flowlogger-0.2.2.dist-info/LICENSE
flowlogger-0.2.2.dist-info/METADATA
flowlogger-0.2.2.dist-info/WHEEL
flowlogger-0.2.2.dist-info/top_level.txt
flowlogger-0.2.2.dist-info/RECORD
