Metadata-Version: 2.1
Name: flowlogger
Version: 0.2.2
Summary: This is a small library for logging while training ML. Current version is 0.2.2, its a feature-poor pre-alpha.
Home-page: https://github.com/oblivisheee/flowlogger
Author: oblivisheee
Author-email: author@gmail.com
Classifier: Programming Language :: Python :: 3
Classifier: License :: OSI Approved :: Apache Software License
Classifier: Operating System :: OS Independent
Requires-Python: >=3.6
License-File: LICENSE
Requires-Dist: GPUtil
Requires-Dist: psutil
